concurrent_coalesce/__init__.py
concurrent_coalesce/core.py
concurrent_coalesce-0.4.0.dist-info/licenses/LICENSE
concurrent_coalesce-0.4.0.dist-info/METADATA
concurrent_coalesce-0.4.0.dist-info/WHEEL
concurrent_coalesce-0.4.0.dist-info/top_level.txt
concurrent_coalesce-0.4.0.dist-info/RECORD
