Metadata-Version: 2.1
Name: concurrent-coalesce
Version: 0.4.0
Summary: A decorator that coalesces concurrent function calls
Home-page: https://github.com/claytonsingh/concurrent-coalesce-python
Author: Clayton Singh
Author-email: claytonsingh@gmail.com
License: MIT License
Project-URL: Bug Tracker, https://github.com/claytonsingh/concurrent-coalesce-python/issues
Project-URL: Homepage, https://github.com/claytonsingh/concurrent-coalesce-python
Project-URL: Repository, https://github.com/claytonsingh/concurrent-coalesce-python
Keywords: concurrent,coalesce,decorator,function,calls
Platform: UNKNOWN
Classifier: Development Status :: 3 - Alpha
Classifier: Programming Language :: Python :: 2.7
Classifier: Programming Language :: Python :: 3.7
Classifier: Programming Language :: Python :: 3.8
Classifier: Programming Language :: Python :: 3.9
Classifier: Programming Language :: Python :: 3.10
Classifier: Programming Language :: Python :: 3.11
Classifier: Programming Language :: Python :: 3.12
Classifier: Programming Language :: Python :: 3.13
Classifier: Operating System :: OS Independent
Requires-Python: >=2.7
